[
{
  "pk": "def11673-d4ab-41a6-a37f-0c6846b96001",
  "model": "ticket.ticketstatus",
  "fields": {
    "name": "ticket.status.draft",
    "deleted": null,
    "modified": "2016-01-20T18:47:56.928Z",
    "created": "2016-01-20T18:47:56.928Z"
  }
},
{
  "pk": "def11673-d4ab-41a6-a37f-0c6846b96002",
  "model": "ticket.ticketstatus",
  "fields": {
    "name": "ticket.status.new",
    "deleted": null,
    "modified": "2016-01-20T18:47:56.933Z",
    "created": "2016-01-20T18:47:56.933Z"
  }
},
{
  "pk": "def11673-d4ab-41a6-a37f-0c6846b96003",
  "model": "ticket.ticketstatus",
  "fields": {
    "name": "ticket.status.in_progress",
    "deleted": null,
    "modified": "2016-01-20T18:47:56.936Z",
    "created": "2016-01-20T18:47:56.936Z"
  }
},
{
  "pk": "def11673-d4ab-41a6-a37f-0c6846b96004",
  "model": "ticket.ticketstatus",
  "fields": {
    "name": "ticket.status.deferred",
    "deleted": null,
    "modified": "2016-01-20T18:47:56.938Z",
    "created": "2016-01-20T18:47:56.938Z"
  }
},
{
  "pk": "def11673-d4ab-41a6-a37f-0c6846b96005",
  "model": "ticket.ticketstatus",
  "fields": {
    "name": "ticket.status.denied",
    "deleted": null,
    "modified": "2016-01-20T18:47:56.940Z",
    "created": "2016-01-20T18:47:56.940Z"
  }
},
{
  "pk": "def11673-d4ab-41a6-a37f-0c6846b96006",
  "model": "ticket.ticketstatus",
  "fields": {
    "name": "ticket.status.problem_solved",
    "deleted": null,
    "modified": "2016-01-20T18:47:56.943Z",
    "created": "2016-01-20T18:47:56.943Z"
  }
},
{
  "pk": "def11673-d4ab-41a6-a37f-0c6846b96007",
  "model": "ticket.ticketstatus",
  "fields": {
    "name": "ticket.status.complete",
    "deleted": null,
    "modified": "2016-01-20T18:47:56.945Z",
    "created": "2016-01-20T18:47:56.945Z"
  }
},
{
  "pk": "def11673-d4ab-41a6-a37f-0c6846b96008",
  "model": "ticket.ticketstatus",
  "fields": {
    "name": "ticket.status.closed",
    "deleted": null,
    "modified": "2016-01-20T18:47:56.947Z",
    "created": "2016-01-20T18:47:56.947Z"
  }
},
{
  "pk": "def11673-d4ab-41a6-a37f-0c6846b96009",
  "model": "ticket.ticketstatus",
  "fields": {
    "name": "ticket.status.unsatisfactory_completion",
    "deleted": null,
    "modified": "2016-01-20T18:47:56.950Z",
    "created": "2016-01-20T18:47:56.950Z"
  }
},
{
  "pk": "def21673-d4ab-41a6-a37f-0c6846b96001",
  "model": "ticket.ticketpriority",
  "fields": {
    "name": "ticket.priority.emergency",
    "deleted": null,
    "modified": "2016-01-20T18:47:56.952Z",
    "created": "2016-01-20T18:47:56.952Z"
  }
},
{
  "pk": "def21673-d4ab-41a6-a37f-0c6846b96002",
  "model": "ticket.ticketpriority",
  "fields": {
    "name": "ticket.priority.high",
    "deleted": null,
    "modified": "2016-01-20T18:47:56.955Z",
    "created": "2016-01-20T18:47:56.955Z"
  }
},
{
  "pk": "def21673-d4ab-41a6-a37f-0c6846b96003",
  "model": "ticket.ticketpriority",
  "fields": {
    "name": "ticket.priority.medium",
    "deleted": null,
    "modified": "2016-01-20T18:47:56.957Z",
    "created": "2016-01-20T18:47:56.957Z"
  }
},
{
  "pk": "def21673-d4ab-41a6-a37f-0c6846b96004",
  "model": "ticket.ticketpriority",
  "fields": {
    "name": "ticket.priority.low",
    "deleted": null,
    "modified": "2016-01-20T18:47:56.959Z",
    "created": "2016-01-20T18:47:56.959Z"
  }
},
{
  "pk": "40f530c4-ce6c-4724-9cfd-37a16e787001",
  "model": "ticket.ticket",
  "fields": {
    "deleted": null,
    "assignee": "30f530c4-ce6c-4724-9cfd-37a16e787157",
    "created": "2016-01-20T18:47:56.979Z",
    "status": "def11673-d4ab-41a6-a37f-0c6846b96002",
    "modified": "2016-01-20T18:47:56.979Z",
    "location": "1674e9cf-4ea9-4043-acbb-5545af11ed41",
    "categories": [
      "24f530c4-ce6c-4724-9cfd-37a16e787003",
      "24f530c4-ce6c-4724-9cfd-37a16e787011",
      "24f530c4-ce6c-4724-9cfd-37a16e787034"
    ],
    "priority": "def21673-d4ab-41a6-a37f-0c6846b96001",
    "requester": "FkoOtPYsLc",
    "number": 1,
    "cc": [
      "30f530c4-ce6c-4724-9cfd-37a16e787102"
    ],
    "request": "lkDPyFISCH"
  }
},
{
  "pk": "40f530c4-ce6c-4724-9cfd-37a16e787002",
  "model": "ticket.ticket",
  "fields": {
    "deleted": null,
    "assignee": "30f530c4-ce6c-4724-9cfd-37a16e787063",
    "created": "2016-01-20T18:47:57.017Z",
    "status": "def11673-d4ab-41a6-a37f-0c6846b96002",
    "modified": "2016-01-20T18:47:57.017Z",
    "location": "107dcfd8-92d4-4b1c-8268-c64c935e7fcc",
    "categories": [
      "24f530c4-ce6c-4724-9cfd-37a16e787003",
      "24f530c4-ce6c-4724-9cfd-37a16e787011",
      "24f530c4-ce6c-4724-9cfd-37a16e787034"
    ],
    "priority": "def21673-d4ab-41a6-a37f-0c6846b96001",
    "requester": "DoKCQbrTAY",
    "number": 2,
    "cc": [
      "30f530c4-ce6c-4724-9cfd-37a16e787012"
    ],
    "request": "tLjIdfjvNu"
  }
},
{
  "pk": "40f530c4-ce6c-4724-9cfd-37a16e787003",
  "model": "ticket.ticket",
  "fields": {
    "deleted": null,
    "assignee": "30f530c4-ce6c-4724-9cfd-37a16e787185",
    "created": "2016-01-20T18:47:57.051Z",
    "status": "def11673-d4ab-41a6-a37f-0c6846b96002",
    "modified": "2016-01-20T18:47:57.051Z",
    "location": "f09e3733-699e-423d-8948-9a98aaf1951c",
    "categories": [
      "24f530c4-ce6c-4724-9cfd-37a16e787003",
      "24f530c4-ce6c-4724-9cfd-37a16e787011",
      "24f530c4-ce6c-4724-9cfd-37a16e787034"
    ],
    "priority": "def21673-d4ab-41a6-a37f-0c6846b96001",
    "requester": "PnHtsPDDLH",
    "number": 3,
    "cc": [
      "30f530c4-ce6c-4724-9cfd-37a16e787006"
    ],
    "request": "slOvjcBzSa"
  }
},
{
  "pk": "40f530c4-ce6c-4724-9cfd-37a16e787004",
  "model": "ticket.ticket",
  "fields": {
    "deleted": null,
    "assignee": "30f530c4-ce6c-4724-9cfd-37a16e787118",
    "created": "2016-01-20T18:47:57.086Z",
    "status": "def11673-d4ab-41a6-a37f-0c6846b96002",
    "modified": "2016-01-20T18:47:57.086Z",
    "location": "107dcfd8-92d4-4b1c-8268-c64c935e7fcc",
    "categories": [
      "24f530c4-ce6c-4724-9cfd-37a16e787003",
      "24f530c4-ce6c-4724-9cfd-37a16e787011",
      "24f530c4-ce6c-4724-9cfd-37a16e787034"
    ],
    "priority": "def21673-d4ab-41a6-a37f-0c6846b96001",
    "requester": "djAEwPqAWV",
    "number": 4,
    "cc": [
      "30f530c4-ce6c-4724-9cfd-37a16e787088"
    ],
    "request": "avOJWlxdDP"
  }
},
{
  "pk": "40f530c4-ce6c-4724-9cfd-37a16e787005",
  "model": "ticket.ticket",
  "fields": {
    "deleted": null,
    "assignee": "30f530c4-ce6c-4724-9cfd-37a16e787104",
    "created": "2016-01-20T18:47:57.119Z",
    "status": "def11673-d4ab-41a6-a37f-0c6846b96002",
    "modified": "2016-01-20T18:47:57.119Z",
    "location": "f09e3733-699e-423d-8948-9a98aaf1951c",
    "categories": [
      "24f530c4-ce6c-4724-9cfd-37a16e787003",
      "24f530c4-ce6c-4724-9cfd-37a16e787011",
      "24f530c4-ce6c-4724-9cfd-37a16e787034"
    ],
    "priority": "def21673-d4ab-41a6-a37f-0c6846b96001",
    "requester": "AMLHYtoFWl",
    "number": 5,
    "cc": [
      "30f530c4-ce6c-4724-9cfd-37a16e787093"
    ],
    "request": "nrspdLJTWN"
  }
},
{
  "pk": "40f530c4-ce6c-4724-9cfd-37a16e787006",
  "model": "ticket.ticket",
  "fields": {
    "deleted": null,
    "assignee": "30f530c4-ce6c-4724-9cfd-37a16e787177",
    "created": "2016-01-20T18:47:57.153Z",
    "status": "def11673-d4ab-41a6-a37f-0c6846b96002",
    "modified": "2016-01-20T18:47:57.153Z",
    "location": "107dcfd8-92d4-4b1c-8268-c64c935e7fcc",
    "categories": [
      "24f530c4-ce6c-4724-9cfd-37a16e787003",
      "24f530c4-ce6c-4724-9cfd-37a16e787011",
      "24f530c4-ce6c-4724-9cfd-37a16e787034"
    ],
    "priority": "def21673-d4ab-41a6-a37f-0c6846b96001",
    "requester": "MFRJxDewfQ",
    "number": 6,
    "cc": [
      "30f530c4-ce6c-4724-9cfd-37a16e787134"
    ],
    "request": "bJNCVeJlEY"
  }
},
{
  "pk": "40f530c4-ce6c-4724-9cfd-37a16e787007",
  "model": "ticket.ticket",
  "fields": {
    "deleted": null,
    "assignee": "30f530c4-ce6c-4724-9cfd-37a16e787059",
    "created": "2016-01-20T18:47:57.186Z",
    "status": "def11673-d4ab-41a6-a37f-0c6846b96002",
    "modified": "2016-01-20T18:47:57.186Z",
    "location": "107dcfd8-92d4-4b1c-8268-c64c935e7fcc",
    "categories": [
      "24f530c4-ce6c-4724-9cfd-37a16e787003",
      "24f530c4-ce6c-4724-9cfd-37a16e787011",
      "24f530c4-ce6c-4724-9cfd-37a16e787034"
    ],
    "priority": "def21673-d4ab-41a6-a37f-0c6846b96001",
    "requester": "HOJvRoEBKO",
    "number": 7,
    "cc": [
      "30f530c4-ce6c-4724-9cfd-37a16e787106"
    ],
    "request": "AGYUWvLfWe"
  }
},
{
  "pk": "40f530c4-ce6c-4724-9cfd-37a16e787008",
  "model": "ticket.ticket",
  "fields": {
    "deleted": null,
    "assignee": "30f530c4-ce6c-4724-9cfd-37a16e787160",
    "created": "2016-01-20T18:47:57.220Z",
    "status": "def11673-d4ab-41a6-a37f-0c6846b96002",
    "modified": "2016-01-20T18:47:57.220Z",
    "location": "589145b7-a520-4954-8bb4-38d188b716b6",
    "categories": [
      "24f530c4-ce6c-4724-9cfd-37a16e787003",
      "24f530c4-ce6c-4724-9cfd-37a16e787011",
      "24f530c4-ce6c-4724-9cfd-37a16e787034"
    ],
    "priority": "def21673-d4ab-41a6-a37f-0c6846b96001",
    "requester": "luWxExlEtb",
    "number": 8,
    "cc": [
      "30f530c4-ce6c-4724-9cfd-37a16e787116"
    ],
    "request": "sAkBDIjOvx"
  }
},
{
  "pk": "40f530c4-ce6c-4724-9cfd-37a16e787009",
  "model": "ticket.ticket",
  "fields": {
    "deleted": null,
    "assignee": "30f530c4-ce6c-4724-9cfd-37a16e787161",
    "created": "2016-01-20T18:47:57.252Z",
    "status": "def11673-d4ab-41a6-a37f-0c6846b96002",
    "modified": "2016-01-20T18:47:57.252Z",
    "location": "dddd7e16-f57a-424f-847f-8bb938b43d0b",
    "categories": [
      "24f530c4-ce6c-4724-9cfd-37a16e787003",
      "24f530c4-ce6c-4724-9cfd-37a16e787011",
      "24f530c4-ce6c-4724-9cfd-37a16e787034"
    ],
    "priority": "def21673-d4ab-41a6-a37f-0c6846b96001",
    "requester": "UIdEKLLRpV",
    "number": 9,
    "cc": [
      "30f530c4-ce6c-4724-9cfd-37a16e787101"
    ],
    "request": "bUeqVfltBF"
  }
},
{
  "pk": "40f530c4-ce6c-4724-9cfd-37a16e787010",
  "model": "ticket.ticket",
  "fields": {
    "deleted": null,
    "assignee": "30f530c4-ce6c-4724-9cfd-37a16e787129",
    "created": "2016-01-20T18:47:57.285Z",
    "status": "def11673-d4ab-41a6-a37f-0c6846b96002",
    "modified": "2016-01-20T18:47:57.285Z",
    "location": "107dcfd8-92d4-4b1c-8268-c64c935e7fcc",
    "categories": [
      "24f530c4-ce6c-4724-9cfd-37a16e787003",
      "24f530c4-ce6c-4724-9cfd-37a16e787011",
      "24f530c4-ce6c-4724-9cfd-37a16e787034"
    ],
    "priority": "def21673-d4ab-41a6-a37f-0c6846b96001",
    "requester": "wgZhmIFWdC",
    "number": 10,
    "cc": [
      "30f530c4-ce6c-4724-9cfd-37a16e787037"
    ],
    "request": "MxKNiwHpeM"
  }
},
{
  "pk": "40f530c4-ce6c-4724-9cfd-37a16e787011",
  "model": "ticket.ticket",
  "fields": {
    "deleted": null,
    "assignee": "30f530c4-ce6c-4724-9cfd-37a16e787047",
    "created": "2016-01-20T18:47:57.318Z",
    "status": "def11673-d4ab-41a6-a37f-0c6846b96002",
    "modified": "2016-01-20T18:47:57.318Z",
    "location": "dddd7e16-f57a-424f-847f-8bb938b43d0b",
    "categories": [
      "24f530c4-ce6c-4724-9cfd-37a16e787003",
      "24f530c4-ce6c-4724-9cfd-37a16e787011",
      "24f530c4-ce6c-4724-9cfd-37a16e787034"
    ],
    "priority": "def21673-d4ab-41a6-a37f-0c6846b96001",
    "requester": "ZAPyGwfXhc",
    "number": 11,
    "cc": [
      "30f530c4-ce6c-4724-9cfd-37a16e787151"
    ],
    "request": "jeGlvocFJO"
  }
},
{
  "pk": "40f530c4-ce6c-4724-9cfd-37a16e787012",
  "model": "ticket.ticket",
  "fields": {
    "deleted": null,
    "assignee": "30f530c4-ce6c-4724-9cfd-37a16e787056",
    "created": "2016-01-20T18:47:57.350Z",
    "status": "def11673-d4ab-41a6-a37f-0c6846b96002",
    "modified": "2016-01-20T18:47:57.350Z",
    "location": "dddd7e16-f57a-424f-847f-8bb938b43d0b",
    "categories": [
      "24f530c4-ce6c-4724-9cfd-37a16e787003",
      "24f530c4-ce6c-4724-9cfd-37a16e787011",
      "24f530c4-ce6c-4724-9cfd-37a16e787034"
    ],
    "priority": "def21673-d4ab-41a6-a37f-0c6846b96001",
    "requester": "nKUZxqIucA",
    "number": 12,
    "cc": [
      "30f530c4-ce6c-4724-9cfd-37a16e787028"
    ],
    "request": "AIAnhFNpVo"
  }
},
{
  "pk": "40f530c4-ce6c-4724-9cfd-37a16e787013",
  "model": "ticket.ticket",
  "fields": {
    "deleted": null,
    "assignee": "30f530c4-ce6c-4724-9cfd-37a16e787172",
    "created": "2016-01-20T18:47:57.383Z",
    "status": "def11673-d4ab-41a6-a37f-0c6846b96002",
    "modified": "2016-01-20T18:47:57.383Z",
    "location": "589145b7-a520-4954-8bb4-38d188b716b6",
    "categories": [
      "24f530c4-ce6c-4724-9cfd-37a16e787003",
      "24f530c4-ce6c-4724-9cfd-37a16e787011",
      "24f530c4-ce6c-4724-9cfd-37a16e787034"
    ],
    "priority": "def21673-d4ab-41a6-a37f-0c6846b96001",
    "requester": "BocylhAKRb",
    "number": 13,
    "cc": [
      "30f530c4-ce6c-4724-9cfd-37a16e787026"
    ],
    "request": "slohVoKOun"
  }
},
{
  "pk": "40f530c4-ce6c-4724-9cfd-37a16e787014",
  "model": "ticket.ticket",
  "fields": {
    "deleted": null,
    "assignee": "30f530c4-ce6c-4724-9cfd-37a16e787013",
    "created": "2016-01-20T18:47:57.416Z",
    "status": "def11673-d4ab-41a6-a37f-0c6846b96002",
    "modified": "2016-01-20T18:47:57.416Z",
    "location": "107dcfd8-92d4-4b1c-8268-c64c935e7fcc",
    "categories": [
      "24f530c4-ce6c-4724-9cfd-37a16e787003",
      "24f530c4-ce6c-4724-9cfd-37a16e787011",
      "24f530c4-ce6c-4724-9cfd-37a16e787034"
    ],
    "priority": "def21673-d4ab-41a6-a37f-0c6846b96001",
    "requester": "iRQeKIXCoX",
    "number": 14,
    "cc": [
      "30f530c4-ce6c-4724-9cfd-37a16e787110"
    ],
    "request": "SGGojdodIZ"
  }
},
{
  "pk": "40f530c4-ce6c-4724-9cfd-37a16e787015",
  "model": "ticket.ticket",
  "fields": {
    "deleted": null,
    "assignee": "30f530c4-ce6c-4724-9cfd-37a16e787108",
    "created": "2016-01-20T18:47:57.448Z",
    "status": "def11673-d4ab-41a6-a37f-0c6846b96002",
    "modified": "2016-01-20T18:47:57.448Z",
    "location": "589145b7-a520-4954-8bb4-38d188b716b6",
    "categories": [
      "24f530c4-ce6c-4724-9cfd-37a16e787003",
      "24f530c4-ce6c-4724-9cfd-37a16e787011",
      "24f530c4-ce6c-4724-9cfd-37a16e787034"
    ],
    "priority": "def21673-d4ab-41a6-a37f-0c6846b96001",
    "requester": "bzaOZWEuSx",
    "number": 15,
    "cc": [
      "30f530c4-ce6c-4724-9cfd-37a16e787060"
    ],
    "request": "KYDTPAsJqa"
  }
},
{
  "pk": "40f530c4-ce6c-4724-9cfd-37a16e787016",
  "model": "ticket.ticket",
  "fields": {
    "deleted": null,
    "assignee": "30f530c4-ce6c-4724-9cfd-37a16e787182",
    "created": "2016-01-20T18:47:57.481Z",
    "status": "def11673-d4ab-41a6-a37f-0c6846b96002",
    "modified": "2016-01-20T18:47:57.481Z",
    "location": "107dcfd8-92d4-4b1c-8268-c64c935e7fcc",
    "categories": [
      "24f530c4-ce6c-4724-9cfd-37a16e787003",
      "24f530c4-ce6c-4724-9cfd-37a16e787011",
      "24f530c4-ce6c-4724-9cfd-37a16e787034"
    ],
    "priority": "def21673-d4ab-41a6-a37f-0c6846b96001",
    "requester": "ZFLJPOuTpJ",
    "number": 16,
    "cc": [
      "30f530c4-ce6c-4724-9cfd-37a16e787025"
    ],
    "request": "XQEFKxLqzO"
  }
},
{
  "pk": "40f530c4-ce6c-4724-9cfd-37a16e787017",
  "model": "ticket.ticket",
  "fields": {
    "deleted": null,
    "assignee": "30f530c4-ce6c-4724-9cfd-37a16e787064",
    "created": "2016-01-20T18:47:57.514Z",
    "status": "def11673-d4ab-41a6-a37f-0c6846b96002",
    "modified": "2016-01-20T18:47:57.514Z",
    "location": "9fa58029-0dbc-4c03-ad09-512298c7f6d4",
    "categories": [
      "24f530c4-ce6c-4724-9cfd-37a16e787003",
      "24f530c4-ce6c-4724-9cfd-37a16e787011",
      "24f530c4-ce6c-4724-9cfd-37a16e787034"
    ],
    "priority": "def21673-d4ab-41a6-a37f-0c6846b96001",
    "requester": "buyBhkXSnB",
    "number": 17,
    "cc": [
      "30f530c4-ce6c-4724-9cfd-37a16e787185"
    ],
    "request": "QeeFoQrnEH"
  }
},
{
  "pk": "40f530c4-ce6c-4724-9cfd-37a16e787018",
  "model": "ticket.ticket",
  "fields": {
    "deleted": null,
    "assignee": "30f530c4-ce6c-4724-9cfd-37a16e787088",
    "created": "2016-01-20T18:47:57.548Z",
    "status": "def11673-d4ab-41a6-a37f-0c6846b96002",
    "modified": "2016-01-20T18:47:57.548Z",
    "location": "1847059c-13fc-429f-b405-e86afd2d67e8",
    "categories": [
      "24f530c4-ce6c-4724-9cfd-37a16e787003",
      "24f530c4-ce6c-4724-9cfd-37a16e787011",
      "24f530c4-ce6c-4724-9cfd-37a16e787034"
    ],
    "priority": "def21673-d4ab-41a6-a37f-0c6846b96001",
    "requester": "NDQooeVsAH",
    "number": 18,
    "cc": [
      "30f530c4-ce6c-4724-9cfd-37a16e787011"
    ],
    "request": "sqhzekROcJ"
  }
},
{
  "pk": "40f530c4-ce6c-4724-9cfd-37a16e787019",
  "model": "ticket.ticket",
  "fields": {
    "deleted": null,
    "assignee": "30f530c4-ce6c-4724-9cfd-37a16e787166",
    "created": "2016-01-20T18:47:57.584Z",
    "status": "def11673-d4ab-41a6-a37f-0c6846b96002",
    "modified": "2016-01-20T18:47:57.584Z",
    "location": "107dcfd8-92d4-4b1c-8268-c64c935e7fcc",
    "categories": [
      "24f530c4-ce6c-4724-9cfd-37a16e787003",
      "24f530c4-ce6c-4724-9cfd-37a16e787011",
      "24f530c4-ce6c-4724-9cfd-37a16e787034"
    ],
    "priority": "def21673-d4ab-41a6-a37f-0c6846b96001",
    "requester": "PfsWMTWaoQ",
    "number": 19,
    "cc": [
      "30f530c4-ce6c-4724-9cfd-37a16e787094"
    ],
    "request": "VFPVZDVKdG"
  }
},
{
  "pk": "40f530c4-ce6c-4724-9cfd-37a16e787020",
  "model": "ticket.ticket",
  "fields": {
    "deleted": null,
    "assignee": "30f530c4-ce6c-4724-9cfd-37a16e787046",
    "created": "2016-01-20T18:47:57.617Z",
    "status": "def11673-d4ab-41a6-a37f-0c6846b96002",
    "modified": "2016-01-20T18:47:57.617Z",
    "location": "9fa58029-0dbc-4c03-ad09-512298c7f6d4",
    "categories": [
      "24f530c4-ce6c-4724-9cfd-37a16e787003",
      "24f530c4-ce6c-4724-9cfd-37a16e787011",
      "24f530c4-ce6c-4724-9cfd-37a16e787034"
    ],
    "priority": "def21673-d4ab-41a6-a37f-0c6846b96001",
    "requester": "AFRWqcpZyh",
    "number": 20,
    "cc": [
      "30f530c4-ce6c-4724-9cfd-37a16e787035"
    ],
    "request": "EUAytKLsYN"
  }
},
{
  "pk": "40f530c4-ce6c-4724-9cfd-37a16e787021",
  "model": "ticket.ticket",
  "fields": {
    "deleted": null,
    "assignee": "30f530c4-ce6c-4724-9cfd-37a16e787132",
    "created": "2016-01-20T18:47:57.650Z",
    "status": "def11673-d4ab-41a6-a37f-0c6846b96002",
    "modified": "2016-01-20T18:47:57.650Z",
    "location": "0e75c4bb-1a11-451f-a8ef-4311df235c26",
    "categories": [
      "24f530c4-ce6c-4724-9cfd-37a16e787003",
      "24f530c4-ce6c-4724-9cfd-37a16e787011",
      "24f530c4-ce6c-4724-9cfd-37a16e787034"
    ],
    "priority": "def21673-d4ab-41a6-a37f-0c6846b96001",
    "requester": "zAKpzlIYZf",
    "number": 21,
    "cc": [
      "30f530c4-ce6c-4724-9cfd-37a16e787038"
    ],
    "request": "HODPQHLJYy"
  }
},
{
  "pk": "40f530c4-ce6c-4724-9cfd-37a16e787022",
  "model": "ticket.ticket",
  "fields": {
    "deleted": null,
    "assignee": "30f530c4-ce6c-4724-9cfd-37a16e787084",
    "created": "2016-01-20T18:47:57.683Z",
    "status": "def11673-d4ab-41a6-a37f-0c6846b96002",
    "modified": "2016-01-20T18:47:57.683Z",
    "location": "9fa58029-0dbc-4c03-ad09-512298c7f6d4",
    "categories": [
      "24f530c4-ce6c-4724-9cfd-37a16e787003",
      "24f530c4-ce6c-4724-9cfd-37a16e787011",
      "24f530c4-ce6c-4724-9cfd-37a16e787034"
    ],
    "priority": "def21673-d4ab-41a6-a37f-0c6846b96001",
    "requester": "nEgarPxnWu",
    "number": 22,
    "cc": [
      "30f530c4-ce6c-4724-9cfd-37a16e787067"
    ],
    "request": "XmodjxUmQv"
  }
},
{
  "pk": "40f530c4-ce6c-4724-9cfd-37a16e787023",
  "model": "ticket.ticket",
  "fields": {
    "deleted": null,
    "assignee": "30f530c4-ce6c-4724-9cfd-37a16e787114",
    "created": "2016-01-20T18:47:57.716Z",
    "status": "def11673-d4ab-41a6-a37f-0c6846b96002",
    "modified": "2016-01-20T18:47:57.716Z",
    "location": "107dcfd8-92d4-4b1c-8268-c64c935e7fcc",
    "categories": [
      "24f530c4-ce6c-4724-9cfd-37a16e787003",
      "24f530c4-ce6c-4724-9cfd-37a16e787011",
      "24f530c4-ce6c-4724-9cfd-37a16e787034"
    ],
    "priority": "def21673-d4ab-41a6-a37f-0c6846b96001",
    "requester": "dPwcnWdnXr",
    "number": 23,
    "cc": [
      "30f530c4-ce6c-4724-9cfd-37a16e787082"
    ],
    "request": "SOCAVfKLVB"
  }
},
{
  "pk": "40f530c4-ce6c-4724-9cfd-37a16e787024",
  "model": "ticket.ticket",
  "fields": {
    "deleted": null,
    "assignee": "30f530c4-ce6c-4724-9cfd-37a16e787143",
    "created": "2016-01-20T18:47:57.750Z",
    "status": "def11673-d4ab-41a6-a37f-0c6846b96002",
    "modified": "2016-01-20T18:47:57.750Z",
    "location": "dddd7e16-f57a-424f-847f-8bb938b43d0b",
    "categories": [
      "24f530c4-ce6c-4724-9cfd-37a16e787003",
      "24f530c4-ce6c-4724-9cfd-37a16e787011",
      "24f530c4-ce6c-4724-9cfd-37a16e787034"
    ],
    "priority": "def21673-d4ab-41a6-a37f-0c6846b96001",
    "requester": "AEfQxCLXOL",
    "number": 24,
    "cc": [
      "30f530c4-ce6c-4724-9cfd-37a16e787136"
    ],
    "request": "eDyjuhcUXx"
  }
},
{
  "pk": "40f530c4-ce6c-4724-9cfd-37a16e787025",
  "model": "ticket.ticket",
  "fields": {
    "deleted": null,
    "assignee": "30f530c4-ce6c-4724-9cfd-37a16e787074",
    "created": "2016-01-20T18:47:57.783Z",
    "status": "def11673-d4ab-41a6-a37f-0c6846b96002",
    "modified": "2016-01-20T18:47:57.783Z",
    "location": "9fa58029-0dbc-4c03-ad09-512298c7f6d4",
    "categories": [
      "24f530c4-ce6c-4724-9cfd-37a16e787003",
      "24f530c4-ce6c-4724-9cfd-37a16e787011",
      "24f530c4-ce6c-4724-9cfd-37a16e787034"
    ],
    "priority": "def21673-d4ab-41a6-a37f-0c6846b96001",
    "requester": "aFkbySlwgT",
    "number": 25,
    "cc": [
      "30f530c4-ce6c-4724-9cfd-37a16e787003"
    ],
    "request": "mmiiiuyBLF"
  }
},
{
  "pk": "40f530c4-ce6c-4724-9cfd-37a16e787026",
  "model": "ticket.ticket",
  "fields": {
    "deleted": null,
    "assignee": "30f530c4-ce6c-4724-9cfd-37a16e787100",
    "created": "2016-01-20T18:47:57.815Z",
    "status": "def11673-d4ab-41a6-a37f-0c6846b96002",
    "modified": "2016-01-20T18:47:57.815Z",
    "location": "a8283447-256c-4701-9dca-e85e952d31f3",
    "categories": [
      "24f530c4-ce6c-4724-9cfd-37a16e787003",
      "24f530c4-ce6c-4724-9cfd-37a16e787011",
      "24f530c4-ce6c-4724-9cfd-37a16e787034"
    ],
    "priority": "def21673-d4ab-41a6-a37f-0c6846b96001",
    "requester": "fQtOVDUhna",
    "number": 26,
    "cc": [
      "30f530c4-ce6c-4724-9cfd-37a16e787156"
    ],
    "request": "ztbZRrHFCy"
  }
},
{
  "pk": "40f530c4-ce6c-4724-9cfd-37a16e787027",
  "model": "ticket.ticket",
  "fields": {
    "deleted": null,
    "assignee": "30f530c4-ce6c-4724-9cfd-37a16e787121",
    "created": "2016-01-20T18:47:57.849Z",
    "status": "def11673-d4ab-41a6-a37f-0c6846b96002",
    "modified": "2016-01-20T18:47:57.849Z",
    "location": "9fa58029-0dbc-4c03-ad09-512298c7f6d4",
    "categories": [
      "24f530c4-ce6c-4724-9cfd-37a16e787003",
      "24f530c4-ce6c-4724-9cfd-37a16e787011",
      "24f530c4-ce6c-4724-9cfd-37a16e787034"
    ],
    "priority": "def21673-d4ab-41a6-a37f-0c6846b96001",
    "requester": "xJBnCgKPnT",
    "number": 27,
    "cc": [
      "30f530c4-ce6c-4724-9cfd-37a16e787129"
    ],
    "request": "JfdmPMnJmH"
  }
},
{
  "pk": "40f530c4-ce6c-4724-9cfd-37a16e787028",
  "model": "ticket.ticket",
  "fields": {
    "deleted": null,
    "assignee": "30f530c4-ce6c-4724-9cfd-37a16e787183",
    "created": "2016-01-20T18:47:57.882Z",
    "status": "def11673-d4ab-41a6-a37f-0c6846b96002",
    "modified": "2016-01-20T18:47:57.882Z",
    "location": "107dcfd8-92d4-4b1c-8268-c64c935e7fcc",
    "categories": [
      "24f530c4-ce6c-4724-9cfd-37a16e787003",
      "24f530c4-ce6c-4724-9cfd-37a16e787011",
      "24f530c4-ce6c-4724-9cfd-37a16e787034"
    ],
    "priority": "def21673-d4ab-41a6-a37f-0c6846b96001",
    "requester": "kFmUvXERkR",
    "number": 28,
    "cc": [
      "30f530c4-ce6c-4724-9cfd-37a16e787130"
    ],
    "request": "pNpQqIvrQn"
  }
},
{
  "pk": "40f530c4-ce6c-4724-9cfd-37a16e787029",
  "model": "ticket.ticket",
  "fields": {
    "deleted": null,
    "assignee": "30f530c4-ce6c-4724-9cfd-37a16e787011",
    "created": "2016-01-20T18:47:57.915Z",
    "status": "def11673-d4ab-41a6-a37f-0c6846b96002",
    "modified": "2016-01-20T18:47:57.915Z",
    "location": "0e75c4bb-1a11-451f-a8ef-4311df235c26",
    "categories": [
      "24f530c4-ce6c-4724-9cfd-37a16e787003",
      "24f530c4-ce6c-4724-9cfd-37a16e787011",
      "24f530c4-ce6c-4724-9cfd-37a16e787034"
    ],
    "priority": "def21673-d4ab-41a6-a37f-0c6846b96001",
    "requester": "JcLzieDlEs",
    "number": 29,
    "cc": [
      "30f530c4-ce6c-4724-9cfd-37a16e787133"
    ],
    "request": "wtJxDVTcdX"
  }
},
{
  "pk": "40f530c4-ce6c-4724-9cfd-37a16e787030",
  "model": "ticket.ticket",
  "fields": {
    "deleted": null,
    "assignee": "30f530c4-ce6c-4724-9cfd-37a16e787171",
    "created": "2016-01-20T18:47:57.948Z",
    "status": "def11673-d4ab-41a6-a37f-0c6846b96002",
    "modified": "2016-01-20T18:47:57.948Z",
    "location": "9fa58029-0dbc-4c03-ad09-512298c7f6d4",
    "categories": [
      "24f530c4-ce6c-4724-9cfd-37a16e787003",
      "24f530c4-ce6c-4724-9cfd-37a16e787011",
      "24f530c4-ce6c-4724-9cfd-37a16e787034"
    ],
    "priority": "def21673-d4ab-41a6-a37f-0c6846b96001",
    "requester": "usopStZMQb",
    "number": 30,
    "cc": [
      "30f530c4-ce6c-4724-9cfd-37a16e787187"
    ],
    "request": "LQrqdqMPlv"
  }
},
{
  "pk": "40f530c4-ce6c-4724-9cfd-37a16e787031",
  "model": "ticket.ticket",
  "fields": {
    "deleted": null,
    "assignee": "30f530c4-ce6c-4724-9cfd-37a16e787170",
    "created": "2016-01-20T18:47:57.981Z",
    "status": "def11673-d4ab-41a6-a37f-0c6846b96002",
    "modified": "2016-01-20T18:47:57.981Z",
    "location": "1674e9cf-4ea9-4043-acbb-5545af11ed41",
    "categories": [
      "24f530c4-ce6c-4724-9cfd-37a16e787003",
      "24f530c4-ce6c-4724-9cfd-37a16e787011",
      "24f530c4-ce6c-4724-9cfd-37a16e787034"
    ],
    "priority": "def21673-d4ab-41a6-a37f-0c6846b96001",
    "requester": "mwqiSdDlDG",
    "number": 31,
    "cc": [
      "30f530c4-ce6c-4724-9cfd-37a16e787130"
    ],
    "request": "cmucsbwPYk"
  }
},
{
  "pk": "40f530c4-ce6c-4724-9cfd-37a16e787032",
  "model": "ticket.ticket",
  "fields": {
    "deleted": null,
    "assignee": "30f530c4-ce6c-4724-9cfd-37a16e787169",
    "created": "2016-01-20T18:47:58.014Z",
    "status": "def11673-d4ab-41a6-a37f-0c6846b96002",
    "modified": "2016-01-20T18:47:58.014Z",
    "location": "1847059c-13fc-429f-b405-e86afd2d67e8",
    "categories": [
      "24f530c4-ce6c-4724-9cfd-37a16e787003",
      "24f530c4-ce6c-4724-9cfd-37a16e787011",
      "24f530c4-ce6c-4724-9cfd-37a16e787034"
    ],
    "priority": "def21673-d4ab-41a6-a37f-0c6846b96001",
    "requester": "EnkXriWPfi",
    "number": 32,
    "cc": [
      "30f530c4-ce6c-4724-9cfd-37a16e787161"
    ],
    "request": "zTUEmzoNBb"
  }
},
{
  "pk": "40f530c4-ce6c-4724-9cfd-37a16e787033",
  "model": "ticket.ticket",
  "fields": {
    "deleted": null,
    "assignee": "30f530c4-ce6c-4724-9cfd-37a16e787128",
    "created": "2016-01-20T18:47:58.065Z",
    "status": "def11673-d4ab-41a6-a37f-0c6846b96002",
    "modified": "2016-01-20T18:47:58.065Z",
    "location": "9fa58029-0dbc-4c03-ad09-512298c7f6d4",
    "categories": [
      "24f530c4-ce6c-4724-9cfd-37a16e787003",
      "24f530c4-ce6c-4724-9cfd-37a16e787011",
      "24f530c4-ce6c-4724-9cfd-37a16e787034"
    ],
    "priority": "def21673-d4ab-41a6-a37f-0c6846b96001",
    "requester": "HSiAlBnOlT",
    "number": 33,
    "cc": [
      "30f530c4-ce6c-4724-9cfd-37a16e787048"
    ],
    "request": "VmmMeocFcs"
  }
},
{
  "pk": "40f530c4-ce6c-4724-9cfd-37a16e787034",
  "model": "ticket.ticket",
  "fields": {
    "deleted": null,
    "assignee": "30f530c4-ce6c-4724-9cfd-37a16e787013",
    "created": "2016-01-20T18:47:58.099Z",
    "status": "def11673-d4ab-41a6-a37f-0c6846b96002",
    "modified": "2016-01-20T18:47:58.099Z",
    "location": "107dcfd8-92d4-4b1c-8268-c64c935e7fcc",
    "categories": [
      "24f530c4-ce6c-4724-9cfd-37a16e787003",
      "24f530c4-ce6c-4724-9cfd-37a16e787011",
      "24f530c4-ce6c-4724-9cfd-37a16e787034"
    ],
    "priority": "def21673-d4ab-41a6-a37f-0c6846b96001",
    "requester": "dbmVjkehIq",
    "number": 34,
    "cc": [
      "30f530c4-ce6c-4724-9cfd-37a16e787056"
    ],
    "request": "GzLrdETMBv"
  }
},
{
  "pk": "40f530c4-ce6c-4724-9cfd-37a16e787035",
  "model": "ticket.ticket",
  "fields": {
    "deleted": null,
    "assignee": "30f530c4-ce6c-4724-9cfd-37a16e787067",
    "created": "2016-01-20T18:47:58.133Z",
    "status": "def11673-d4ab-41a6-a37f-0c6846b96002",
    "modified": "2016-01-20T18:47:58.133Z",
    "location": "9fa58029-0dbc-4c03-ad09-512298c7f6d4",
    "categories": [
      "24f530c4-ce6c-4724-9cfd-37a16e787003",
      "24f530c4-ce6c-4724-9cfd-37a16e787011",
      "24f530c4-ce6c-4724-9cfd-37a16e787034"
    ],
    "priority": "def21673-d4ab-41a6-a37f-0c6846b96001",
    "requester": "NCNTQNInhi",
    "number": 35,
    "cc": [
      "30f530c4-ce6c-4724-9cfd-37a16e787098"
    ],
    "request": "KWAcjlnTtX"
  }
},
{
  "pk": "40f530c4-ce6c-4724-9cfd-37a16e787036",
  "model": "ticket.ticket",
  "fields": {
    "deleted": null,
    "assignee": "30f530c4-ce6c-4724-9cfd-37a16e787106",
    "created": "2016-01-20T18:47:58.166Z",
    "status": "def11673-d4ab-41a6-a37f-0c6846b96002",
    "modified": "2016-01-20T18:47:58.166Z",
    "location": "dddd7e16-f57a-424f-847f-8bb938b43d0b",
    "categories": [
      "24f530c4-ce6c-4724-9cfd-37a16e787003",
      "24f530c4-ce6c-4724-9cfd-37a16e787011",
      "24f530c4-ce6c-4724-9cfd-37a16e787034"
    ],
    "priority": "def21673-d4ab-41a6-a37f-0c6846b96001",
    "requester": "VasJeUtLZl",
    "number": 36,
    "cc": [
      "30f530c4-ce6c-4724-9cfd-37a16e787153"
    ],
    "request": "WOKhAeRzSV"
  }
},
{
  "pk": "40f530c4-ce6c-4724-9cfd-37a16e787037",
  "model": "ticket.ticket",
  "fields": {
    "deleted": null,
    "assignee": "30f530c4-ce6c-4724-9cfd-37a16e787150",
    "created": "2016-01-20T18:47:58.198Z",
    "status": "def11673-d4ab-41a6-a37f-0c6846b96002",
    "modified": "2016-01-20T18:47:58.198Z",
    "location": "589145b7-a520-4954-8bb4-38d188b716b6",
    "categories": [
      "24f530c4-ce6c-4724-9cfd-37a16e787003",
      "24f530c4-ce6c-4724-9cfd-37a16e787011",
      "24f530c4-ce6c-4724-9cfd-37a16e787034"
    ],
    "priority": "def21673-d4ab-41a6-a37f-0c6846b96001",
    "requester": "KidOmeSPZu",
    "number": 37,
    "cc": [
      "30f530c4-ce6c-4724-9cfd-37a16e787065"
    ],
    "request": "aUabQOyIzE"
  }
},
{
  "pk": "40f530c4-ce6c-4724-9cfd-37a16e787038",
  "model": "ticket.ticket",
  "fields": {
    "deleted": null,
    "assignee": "30f530c4-ce6c-4724-9cfd-37a16e787130",
    "created": "2016-01-20T18:47:58.231Z",
    "status": "def11673-d4ab-41a6-a37f-0c6846b96002",
    "modified": "2016-01-20T18:47:58.231Z",
    "location": "1847059c-13fc-429f-b405-e86afd2d67e8",
    "categories": [
      "24f530c4-ce6c-4724-9cfd-37a16e787003",
      "24f530c4-ce6c-4724-9cfd-37a16e787011",
      "24f530c4-ce6c-4724-9cfd-37a16e787034"
    ],
    "priority": "def21673-d4ab-41a6-a37f-0c6846b96001",
    "requester": "STlkuKqQoR",
    "number": 38,
    "cc": [
      "30f530c4-ce6c-4724-9cfd-37a16e787103"
    ],
    "request": "gegRytVmKD"
  }
},
{
  "pk": "40f530c4-ce6c-4724-9cfd-37a16e787039",
  "model": "ticket.ticket",
  "fields": {
    "deleted": null,
    "assignee": "30f530c4-ce6c-4724-9cfd-37a16e787088",
    "created": "2016-01-20T18:47:58.264Z",
    "status": "def11673-d4ab-41a6-a37f-0c6846b96002",
    "modified": "2016-01-20T18:47:58.264Z",
    "location": "1847059c-13fc-429f-b405-e86afd2d67e8",
    "categories": [
      "24f530c4-ce6c-4724-9cfd-37a16e787003",
      "24f530c4-ce6c-4724-9cfd-37a16e787011",
      "24f530c4-ce6c-4724-9cfd-37a16e787034"
    ],
    "priority": "def21673-d4ab-41a6-a37f-0c6846b96001",
    "requester": "jssVgljiol",
    "number": 39,
    "cc": [
      "30f530c4-ce6c-4724-9cfd-37a16e787171"
    ],
    "request": "yQlmNbluxX"
  }
},
{
  "pk": "40f530c4-ce6c-4724-9cfd-37a16e787040",
  "model": "ticket.ticket",
  "fields": {
    "deleted": null,
    "assignee": "30f530c4-ce6c-4724-9cfd-37a16e787089",
    "created": "2016-01-20T18:47:58.298Z",
    "status": "def11673-d4ab-41a6-a37f-0c6846b96002",
    "modified": "2016-01-20T18:47:58.298Z",
    "location": "1674e9cf-4ea9-4043-acbb-5545af11ed41",
    "categories": [
      "24f530c4-ce6c-4724-9cfd-37a16e787003",
      "24f530c4-ce6c-4724-9cfd-37a16e787011",
      "24f530c4-ce6c-4724-9cfd-37a16e787034"
    ],
    "priority": "def21673-d4ab-41a6-a37f-0c6846b96001",
    "requester": "cYfAXRwktk",
    "number": 40,
    "cc": [
      "30f530c4-ce6c-4724-9cfd-37a16e787122"
    ],
    "request": "yqMfnQQOXo"
  }
},
{
  "pk": "40f530c4-ce6c-4724-9cfd-37a16e787041",
  "model": "ticket.ticket",
  "fields": {
    "deleted": null,
    "assignee": "30f530c4-ce6c-4724-9cfd-37a16e787183",
    "created": "2016-01-20T18:47:58.331Z",
    "status": "def11673-d4ab-41a6-a37f-0c6846b96002",
    "modified": "2016-01-20T18:47:58.331Z",
    "location": "107dcfd8-92d4-4b1c-8268-c64c935e7fcc",
    "categories": [
      "24f530c4-ce6c-4724-9cfd-37a16e787003",
      "24f530c4-ce6c-4724-9cfd-37a16e787011",
      "24f530c4-ce6c-4724-9cfd-37a16e787034"
    ],
    "priority": "def21673-d4ab-41a6-a37f-0c6846b96001",
    "requester": "SQHVMmgiKN",
    "number": 41,
    "cc": [
      "30f530c4-ce6c-4724-9cfd-37a16e787141"
    ],
    "request": "CDWuSgmcAv"
  }
},
{
  "pk": "40f530c4-ce6c-4724-9cfd-37a16e787042",
  "model": "ticket.ticket",
  "fields": {
    "deleted": null,
    "assignee": "30f530c4-ce6c-4724-9cfd-37a16e787129",
    "created": "2016-01-20T18:47:58.365Z",
    "status": "def11673-d4ab-41a6-a37f-0c6846b96002",
    "modified": "2016-01-20T18:47:58.365Z",
    "location": "107dcfd8-92d4-4b1c-8268-c64c935e7fcc",
    "categories": [
      "24f530c4-ce6c-4724-9cfd-37a16e787003",
      "24f530c4-ce6c-4724-9cfd-37a16e787011",
      "24f530c4-ce6c-4724-9cfd-37a16e787034"
    ],
    "priority": "def21673-d4ab-41a6-a37f-0c6846b96001",
    "requester": "YxYQpJhzYW",
    "number": 42,
    "cc": [
      "30f530c4-ce6c-4724-9cfd-37a16e787033"
    ],
    "request": "oTtuWEVfdA"
  }
},
{
  "pk": "40f530c4-ce6c-4724-9cfd-37a16e787043",
  "model": "ticket.ticket",
  "fields": {
    "deleted": null,
    "assignee": "30f530c4-ce6c-4724-9cfd-37a16e787050",
    "created": "2016-01-20T18:47:58.398Z",
    "status": "def11673-d4ab-41a6-a37f-0c6846b96002",
    "modified": "2016-01-20T18:47:58.398Z",
    "location": "dddd7e16-f57a-424f-847f-8bb938b43d0b",
    "categories": [
      "24f530c4-ce6c-4724-9cfd-37a16e787003",
      "24f530c4-ce6c-4724-9cfd-37a16e787011",
      "24f530c4-ce6c-4724-9cfd-37a16e787034"
    ],
    "priority": "def21673-d4ab-41a6-a37f-0c6846b96001",
    "requester": "sNzNTHtNSf",
    "number": 43,
    "cc": [
      "30f530c4-ce6c-4724-9cfd-37a16e787109"
    ],
    "request": "oySWUJUCvS"
  }
},
{
  "pk": "40f530c4-ce6c-4724-9cfd-37a16e787044",
  "model": "ticket.ticket",
  "fields": {
    "deleted": null,
    "assignee": "30f530c4-ce6c-4724-9cfd-37a16e787153",
    "created": "2016-01-20T18:47:58.431Z",
    "status": "def11673-d4ab-41a6-a37f-0c6846b96002",
    "modified": "2016-01-20T18:47:58.431Z",
    "location": "a8283447-256c-4701-9dca-e85e952d31f3",
    "categories": [
      "24f530c4-ce6c-4724-9cfd-37a16e787003",
      "24f530c4-ce6c-4724-9cfd-37a16e787011",
      "24f530c4-ce6c-4724-9cfd-37a16e787034"
    ],
    "priority": "def21673-d4ab-41a6-a37f-0c6846b96001",
    "requester": "qZzwexFuhq",
    "number": 44,
    "cc": [
      "30f530c4-ce6c-4724-9cfd-37a16e787050"
    ],
    "request": "UnSjRqVrxH"
  }
},
{
  "pk": "40f530c4-ce6c-4724-9cfd-37a16e787045",
  "model": "ticket.ticket",
  "fields": {
    "deleted": null,
    "assignee": "30f530c4-ce6c-4724-9cfd-37a16e787065",
    "created": "2016-01-20T18:47:58.464Z",
    "status": "def11673-d4ab-41a6-a37f-0c6846b96002",
    "modified": "2016-01-20T18:47:58.464Z",
    "location": "589145b7-a520-4954-8bb4-38d188b716b6",
    "categories": [
      "24f530c4-ce6c-4724-9cfd-37a16e787003",
      "24f530c4-ce6c-4724-9cfd-37a16e787011",
      "24f530c4-ce6c-4724-9cfd-37a16e787034"
    ],
    "priority": "def21673-d4ab-41a6-a37f-0c6846b96001",
    "requester": "BTgAsDGUEF",
    "number": 45,
    "cc": [
      "30f530c4-ce6c-4724-9cfd-37a16e787018"
    ],
    "request": "AbErLAiaIZ"
  }
},
{
  "pk": "40f530c4-ce6c-4724-9cfd-37a16e787046",
  "model": "ticket.ticket",
  "fields": {
    "deleted": null,
    "assignee": "30f530c4-ce6c-4724-9cfd-37a16e787170",
    "created": "2016-01-20T18:47:58.497Z",
    "status": "def11673-d4ab-41a6-a37f-0c6846b96002",
    "modified": "2016-01-20T18:47:58.497Z",
    "location": "1674e9cf-4ea9-4043-acbb-5545af11ed41",
    "categories": [
      "24f530c4-ce6c-4724-9cfd-37a16e787003",
      "24f530c4-ce6c-4724-9cfd-37a16e787011",
      "24f530c4-ce6c-4724-9cfd-37a16e787034"
    ],
    "priority": "def21673-d4ab-41a6-a37f-0c6846b96001",
    "requester": "PDuiQzYvuK",
    "number": 46,
    "cc": [
      "30f530c4-ce6c-4724-9cfd-37a16e787013"
    ],
    "request": "WMZZOWIKiz"
  }
},
{
  "pk": "40f530c4-ce6c-4724-9cfd-37a16e787047",
  "model": "ticket.ticket",
  "fields": {
    "deleted": null,
    "assignee": "30f530c4-ce6c-4724-9cfd-37a16e787102",
    "created": "2016-01-20T18:47:58.530Z",
    "status": "def11673-d4ab-41a6-a37f-0c6846b96002",
    "modified": "2016-01-20T18:47:58.530Z",
    "location": "0e75c4bb-1a11-451f-a8ef-4311df235c26",
    "categories": [
      "24f530c4-ce6c-4724-9cfd-37a16e787003",
      "24f530c4-ce6c-4724-9cfd-37a16e787011",
      "24f530c4-ce6c-4724-9cfd-37a16e787034"
    ],
    "priority": "def21673-d4ab-41a6-a37f-0c6846b96001",
    "requester": "xliqjFRPUJ",
    "number": 47,
    "cc": [
      "30f530c4-ce6c-4724-9cfd-37a16e787012"
    ],
    "request": "OqYqRwqqaj"
  }
},
{
  "pk": "40f530c4-ce6c-4724-9cfd-37a16e787048",
  "model": "ticket.ticket",
  "fields": {
    "deleted": null,
    "assignee": "30f530c4-ce6c-4724-9cfd-37a16e787155",
    "created": "2016-01-20T18:47:58.563Z",
    "status": "def11673-d4ab-41a6-a37f-0c6846b96002",
    "modified": "2016-01-20T18:47:58.563Z",
    "location": "f09e3733-699e-423d-8948-9a98aaf1951c",
    "categories": [
      "24f530c4-ce6c-4724-9cfd-37a16e787003",
      "24f530c4-ce6c-4724-9cfd-37a16e787011",
      "24f530c4-ce6c-4724-9cfd-37a16e787034"
    ],
    "priority": "def21673-d4ab-41a6-a37f-0c6846b96001",
    "requester": "yvDVXchqDE",
    "number": 48,
    "cc": [
      "30f530c4-ce6c-4724-9cfd-37a16e787112"
    ],
    "request": "wCkFAmNXYe"
  }
},
{
  "pk": "40f530c4-ce6c-4724-9cfd-37a16e787049",
  "model": "ticket.ticket",
  "fields": {
    "deleted": null,
    "assignee": "30f530c4-ce6c-4724-9cfd-37a16e787081",
    "created": "2016-01-20T18:47:58.596Z",
    "status": "def11673-d4ab-41a6-a37f-0c6846b96002",
    "modified": "2016-01-20T18:47:58.596Z",
    "location": "a8283447-256c-4701-9dca-e85e952d31f3",
    "categories": [
      "24f530c4-ce6c-4724-9cfd-37a16e787003",
      "24f530c4-ce6c-4724-9cfd-37a16e787011",
      "24f530c4-ce6c-4724-9cfd-37a16e787034"
    ],
    "priority": "def21673-d4ab-41a6-a37f-0c6846b96001",
    "requester": "XiAJpxwutU",
    "number": 49,
    "cc": [
      "30f530c4-ce6c-4724-9cfd-37a16e787068"
    ],
    "request": "GcgOyAMRKX"
  }
},
{
  "pk": "40f530c4-ce6c-4724-9cfd-37a16e787050",
  "model": "ticket.ticket",
  "fields": {
    "deleted": null,
    "assignee": "30f530c4-ce6c-4724-9cfd-37a16e787090",
    "created": "2016-01-20T18:47:58.629Z",
    "status": "def11673-d4ab-41a6-a37f-0c6846b96002",
    "modified": "2016-01-20T18:47:58.629Z",
    "location": "f09e3733-699e-423d-8948-9a98aaf1951c",
    "categories": [
      "24f530c4-ce6c-4724-9cfd-37a16e787003",
      "24f530c4-ce6c-4724-9cfd-37a16e787011",
      "24f530c4-ce6c-4724-9cfd-37a16e787034"
    ],
    "priority": "def21673-d4ab-41a6-a37f-0c6846b96001",
    "requester": "LQUVLfFWpk",
    "number": 50,
    "cc": [
      "30f530c4-ce6c-4724-9cfd-37a16e787071"
    ],
    "request": "OmrDxVzjvP"
  }
},
{
  "pk": "40f530c4-ce6c-4724-9cfd-37a16e787051",
  "model": "ticket.ticket",
  "fields": {
    "deleted": null,
    "assignee": "30f530c4-ce6c-4724-9cfd-37a16e787034",
    "created": "2016-01-20T18:47:58.662Z",
    "status": "def11673-d4ab-41a6-a37f-0c6846b96002",
    "modified": "2016-01-20T18:47:58.662Z",
    "location": "589145b7-a520-4954-8bb4-38d188b716b6",
    "categories": [
      "24f530c4-ce6c-4724-9cfd-37a16e787003",
      "24f530c4-ce6c-4724-9cfd-37a16e787011",
      "24f530c4-ce6c-4724-9cfd-37a16e787034"
    ],
    "priority": "def21673-d4ab-41a6-a37f-0c6846b96001",
    "requester": "nZJGtvroUG",
    "number": 51,
    "cc": [
      "30f530c4-ce6c-4724-9cfd-37a16e787171"
    ],
    "request": "imEmnUQfsU"
  }
}
]
